spark_dql_tools/__init__.py
spark_dql_tools/functions/__init__.py
spark_dql_tools/functions/generator.py
spark_dql_tools/utils/__init__.py
spark_dql_tools/utils/utilitty.py
spark_dql_tools/utils/resource/rules.json
spark_dql_tools-0.7.2.dist-info/LICENSE
spark_dql_tools-0.7.2.dist-info/METADATA
spark_dql_tools-0.7.2.dist-info/WHEEL
spark_dql_tools-0.7.2.dist-info/top_level.txt
spark_dql_tools-0.7.2.dist-info/RECORD
